{
    "id": "122157895568719917",
    "set_id": "pb.61571597523226.-2207520000",
    "username": "Imbolg Harmony ",
    "user_id": "61571597523226",
    "user_pfbid": "",
    "caption": "💙🐾 Anima Samuel Imbolg Harmony\nZADANÝ 🙏",
    "date": "2026-03-06 09:42:55",
    "url": "https://scontent-prg1-1.xx.fbcdn.net/v/t39.30808-6/648231567_122157895574719917_2441207826651281495_n.jpg?_nc_cat=105&ccb=1-7&_nc_sid=7b2446&_nc_ohc=nADEfesDygkQ7kNvwFi50HX&_nc_oc=AdoeqP1kyt2LXEB187O5qmpXNom1u2DGrh2etyLBNc1S4loacvZWRs9VuZ4Rmgg9nCI&_nc_zt=23&_nc_ht=scontent-prg1-1.xx&_nc_gid=EtltIE-iCF7ay3zc2Az3Ug&_nc_ss=7a389&oh=00_Af12lg2Q7J90JDEpTniNW73fHSFmwFxvIMcAmkF08h2EAw&oe=69DB1301",
    "next_photo_id": "122157895520719917",
    "filename": "648231567_122157895574719917_2441207826651281495_n",
    "extension": "jpg",
    "followups_ids": [],
    "num": 36,
    "title": "Imbolg Harmony 's Photos",
    "first_photo_id": "122159709440719917",
    "category": "facebook",
    "subcategory": "photos"
}
